django_temp_permissions/__init__.py
django_temp_permissions/admin.py
django_temp_permissions/apps.py
django_temp_permissions/backends.py
django_temp_permissions/checks.py
django_temp_permissions/exceptions.py
django_temp_permissions/models.py
django_temp_permissions/signals.py
django_temp_permissions/validators.py
django_temp_permissions/migrations/0001_initial.py
django_temp_permissions/migrations/__init__.py
django_temp_permissions-0.4.0.dist-info/METADATA
django_temp_permissions-0.4.0.dist-info/WHEEL
django_temp_permissions-0.4.0.dist-info/licenses/LICENSE.md
django_temp_permissions-0.4.0.dist-info/RECORD
