Metadata-Version: 2.4
Name: django-temp-permissions
Version: 0.4.0
License-File: LICENSE.md
Classifier: Environment :: Web Environment
Classifier: Framework :: Django
Classifier: Framework :: Django :: 4.2
Classifier: Framework :: Django :: 5.2
Classifier: Intended Audience :: Developers
Classifier: Operating System :: OS Independent
Classifier: Programming Language :: Python :: 3 :: Only
Classifier: Programming Language :: Python :: 3.10
Classifier: Programming Language :: Python :: 3.11
Classifier: Programming Language :: Python :: 3.12
Classifier: Programming Language :: Python :: 3.13
Requires-Python: >=3.10
Requires-Dist: django==4.2
Provides-Extra: extra-admin
Requires-Dist: django-admin-extra-buttons; extra == 'extra-admin'
Requires-Dist: django-adminfilters; extra == 'extra-admin'
